envi/__init__.py
envi/envi.py
envi/manager.py
envi-0.2.2.dist-info/METADATA
envi-0.2.2.dist-info/RECORD
envi-0.2.2.dist-info/WHEEL
envi-0.2.2.dist-info/top_level.txt
