Metadata-Version: 2.1
Name: envi
Version: 0.2.2
Summary: Minimal environment variables reader
Home-page: https://github.com/OvalMoney/envi
Author: Walter Danilo Galante
Author-email: walterdangalante@gmail.com
License: MIT license
Keywords: envi
Platform: UNKNOWN
Classifier: Development Status :: 2 - Pre-Alpha
Classifier: Intended Audience :: Developers
Classifier: License :: OSI Approved :: MIT License
Classifier: Natural Language :: English
Classifier: Programming Language :: Python :: 3
Classifier: Programming Language :: Python :: 3.4
Classifier: Programming Language :: Python :: 3.5
Classifier: Programming Language :: Python :: 3.6
